two048/__init__.py
two048/main.py
two048-1.0.2.dist-info/LICENSE
two048-1.0.2.dist-info/METADATA
two048-1.0.2.dist-info/WHEEL
two048-1.0.2.dist-info/top_level.txt
two048-1.0.2.dist-info/RECORD
